[
    { "type": "prefix", "value": "Stone", "theme": ["Medieval Fantasy"], "tier": ["Apprentice", "Artisan", "Architect"] },
    { "type": "prefix", "value": "Ash", "theme": ["Medieval Fantasy"], "tier": ["Apprentice", "Artisan", "Architect"] },
    { "type": "prefix", "value": "Raven", "theme": ["Medieval Fantasy"], "tier": ["Apprentice", "Artisan", "Architect"] },
    { "type": "prefix", "value": "Green", "theme": ["Medieval Fantasy"], "tier": ["Apprentice", "Artisan", "Architect"] },
    { "type": "prefix", "value": "Silver", "theme": ["Medieval Fantasy"], "tier": ["Apprentice", "Artisan", "Architect"] },
    { "type": "prefix", "value": "Gold", "theme": ["Medieval Fantasy"], "wealth": ["Wealthy", "Affluent"], "tier": ["Apprentice", "Artisan", "Architect"] },
    { "type": "prefix", "value": "Iron", "theme": ["Medieval Fantasy"], "tier": ["Apprentice", "Artisan", "Architect"] },
    { "type": "prefix", "value": "Oak", "theme": ["Medieval Fantasy"], "terrain": ["Forest"], "tier": ["Apprentice", "Artisan", "Architect"] },
    { "type": "prefix", "value": "Old", "theme": ["Medieval Fantasy"], "tier": ["Apprentice", "Artisan", "Architect"] },
    { "type": "prefix", "value": "High", "theme": ["Medieval Fantasy"], "size": ["City", "Metropolis"], "tier": ["Apprentice", "Artisan", "Architect"] },
    { "type": "prefix", "value": "Shadow", "theme": ["Medieval Fantasy"], "tier": ["Apprentice", "Artisan", "Architect"] },
    { "type": "prefix", "value": "Ever", "theme": ["Medieval Fantasy"], "tier": ["Apprentice", "Artisan", "Architect"] },

    { "type": "prefix", "value": "Frost", "theme": ["Medieval Fantasy"], "climate": ["Polar"], "terrain": ["Tundra", "Mountains"], "tier": ["Apprentice", "Artisan", "Architect"] },
    { "type": "prefix", "value": "Sun", "theme": ["Medieval Fantasy"], "climate": ["Dry", "Tropical"], "terrain": ["Desert", "Plains"], "tier": ["Apprentice", "Artisan", "Architect"] },
    { "type": "prefix", "value": "Storm", "theme": ["Medieval Fantasy"], "terrain": ["Coast", "Mountains"], "climate": ["Temperate", "Tropical"], "tier": ["Apprentice", "Artisan", "Architect"] },
    { "type": "prefix", "value": "River", "theme": ["Medieval Fantasy"], "terrain": ["River", "Plains"], "tier": ["Apprentice", "Artisan", "Architect"] },
    { "type": "prefix", "value": "Marsh", "theme": ["Medieval Fantasy"], "terrain": ["Swamp"], "tier": ["Apprentice", "Artisan", "Architect"] },
    { "type": "prefix", "value": "Shadow", "theme": ["Medieval Fantasy"], "terrain": ["Forest", "Underground"], "tags": ["Hidden", "Criminal Hideout"], "tier": ["Apprentice", "Artisan", "Architect"] },
    { "type": "prefix", "value": "Ember", "theme": ["Medieval Fantasy"], "terrain": ["Volcanic"], "climate": ["Dry"], "tier": ["Apprentice", "Artisan", "Architect"] },
    { "type": "prefix", "value": "Crystal", "theme": ["Medieval Fantasy"], "terrain": ["Mountains"], "magic": ["High", "Mythic"], "tier": ["Apprentice", "Artisan", "Architect"] },
    { "type": "prefix", "value": "Dune", "theme": ["Medieval Fantasy"], "terrain": ["Desert"], "tier": ["Apprentice", "Artisan", "Architect"] },
    { "type": "prefix", "value": "Mist", "theme": ["Medieval Fantasy"], "terrain": ["Swamp", "Coast"], "tier": ["Apprentice", "Artisan", "Architect"] },
    { "type": "prefix", "value": "Briar", "theme": ["Medieval Fantasy"], "terrain": ["Forest"], "climate": ["Temperate", "Continental"], "tier": ["Apprentice", "Artisan", "Architect"] },


    { "type": "prefix", "value": "Mud", "theme": ["Medieval Fantasy"], "wealth": ["Impoverished", "Struggling"], "terrain": ["Swamp", "Plains"], "tier": ["Apprentice", "Artisan", "Architect"] },
    { "type": "prefix", "value": "Rust", "theme": ["Medieval Fantasy"], "wealth": ["Struggling"], "tags": ["Mining Camp"], "tier": ["Apprentice", "Artisan", "Architect"] },
    { "type": "prefix", "value": "Crown", "theme": ["Medieval Fantasy"], "wealth": ["Affluent", "Wealthy"], "tags": ["Capital"], "tier": ["Apprentice", "Artisan", "Architect"] },
    { "type": "prefix", "value": "Bright", "theme": ["Medieval Fantasy"], "wealth": ["Wealthy", "Modest"], "tier": ["Apprentice", "Artisan", "Architect"] },
    { "type": "prefix", "value": "Dull", "theme": ["Medieval Fantasy"], "wealth": ["Impoverished", "Struggling"], "tier": ["Apprentice", "Artisan", "Architect"] },

    { "type": "prefix", "value": "Myst", "theme": ["Medieval Fantasy"], "magic": ["High", "Mythic"], "tier": ["Apprentice", "Artisan", "Architect"] },
    { "type": "prefix", "value": "Star", "theme": ["Medieval Fantasy"], "magic": ["High", "Mythic"], "climate": ["Continental", "Polar"], "tier": ["Apprentice", "Artisan", "Architect"] },
    { "type": "prefix", "value": "Moon", "theme": ["Medieval Fantasy"], "magic": ["Moderate", "High"], "terrain": ["Forest", "Plains"], "tier": ["Apprentice", "Artisan", "Architect"] },
    { "type": "prefix", "value": "Rune", "theme": ["Medieval Fantasy"], "magic": ["High"], "tags": ["Arcane Nexus"], "tier": ["Apprentice", "Artisan", "Architect"] },
    { "type": "prefix", "value": "Void", "theme": ["Medieval Fantasy"], "magic": ["Mythic"], "tags": ["Ancient Ruins"], "tier": ["Apprentice", "Artisan", "Architect"] },

    { "type": "prefix", "value": "Harbor", "theme": ["Medieval Fantasy"], "tags": ["Port", "Fishing"], "terrain": ["Coast", "River"], "tier": ["Apprentice", "Artisan", "Architect"] },
    { "type": "prefix", "value": "Fort", "theme": ["Medieval Fantasy"], "tags": ["Fortress", "Garrison", "Military Outpost"], "tier": ["Apprentice", "Artisan", "Architect"] },
    { "type": "prefix", "value": "Sacred", "theme": ["Medieval Fantasy"], "tags": ["Sacred Site", "Druidic"], "tier": ["Apprentice", "Artisan", "Architect"] },
    { "type": "prefix", "value": "Trade", "theme": ["Medieval Fantasy"], "tags": ["Trade Hub"], "tier": ["Apprentice", "Artisan", "Architect"] },
    { "type": "prefix", "value": "Nomad", "theme": ["Medieval Fantasy"], "tags": ["Nomadic"], "size": ["Encampment", "Thorp", "Hamlet"], "tier": ["Apprentice", "Artisan", "Architect"] },
    { "type": "prefix", "value": "Prison", "theme": ["Medieval Fantasy"], "tags": ["Prison Settlement"], "tier": ["Apprentice", "Artisan", "Architect"] },
    { "type": "prefix", "value": "Grave", "theme": ["Medieval Fantasy"], "tags": ["Ancient Ruins", "Infested"], "tier": ["Apprentice", "Artisan", "Architect"] },

    { "type": "prefix", "value": "Al", "theme": ["Arabic-inspired"], "tier": ["Artisan", "Architect"] },
    { "type": "prefix", "value": "Dar", "theme": ["Arabic-inspired"], "tier": ["Artisan", "Architect"] },
    { "type": "prefix", "value": "Qal", "theme": ["Arabic-inspired"], "tier": ["Artisan", "Architect"] },
    { "type": "prefix", "value": "Masr", "theme": ["Arabic-inspired"], "tier": ["Artisan", "Architect"] },
    { "type": "prefix", "value": "Jabal", "theme": ["Arabic-inspired"], "tier": ["Artisan", "Architect"] },
    { "type": "prefix", "value": "Ras", "theme": ["Arabic-inspired"], "tier": ["Artisan", "Architect"] },
    { "type": "prefix", "value": "Bait", "theme": ["Arabic-inspired"], "tier": ["Artisan", "Architect"] },
    { "type": "prefix", "value": "Wadi", "theme": ["Arabic-inspired"], "tier": ["Artisan", "Architect"] },
    { "type": "prefix", "value": "Sidi", "theme": ["Arabic-inspired"], "tier": ["Artisan", "Architect"] },
    { "type": "prefix", "value": "Qasr", "theme": ["Arabic-inspired"], "tier": ["Artisan", "Architect"] },

    { "type": "prefix", "value": "Elen", "theme": ["Elven-inspired"], "tier": ["Apprentice", "Artisan", "Architect"] },
    { "type": "prefix", "value": "Faer", "theme": ["Elven-inspired"], "tier": ["Apprentice", "Artisan", "Architect"] },
    { "type": "prefix", "value": "Lúth", "theme": ["Elven-inspired"], "tier": ["Apprentice", "Artisan", "Architect"] },
    { "type": "prefix", "value": "Ael", "theme": ["Elven-inspired"], "tier": ["Apprentice", "Artisan", "Architect"] },
    { "type": "prefix", "value": "Syl", "theme": ["Elven-inspired"], "tier": ["Apprentice", "Artisan", "Architect"] },
    { "type": "prefix", "value": "Thal", "theme": ["Elven-inspired"], "tier": ["Apprentice", "Artisan", "Architect"] },
    { "type": "prefix", "value": "Ithil", "theme": ["Elven-inspired"], "tier": ["Apprentice", "Artisan", "Architect"] },
    { "type": "prefix", "value": "Gal", "theme": ["Elven-inspired"], "tier": ["Apprentice", "Artisan", "Architect"] },
    { "type": "prefix", "value": "Ar", "theme": ["Elven-inspired"], "tier": ["Apprentice", "Artisan", "Architect"] },
    { "type": "prefix", "value": "Ery", "theme": ["Elven-inspired"], "tier": ["Apprentice", "Artisan", "Architect"] },
    { "type": "prefix", "value": "Galad", "theme": ["Elven-inspired"], "tier": ["Apprentice", "Artisan", "Architect"] },
    { "type": "prefix", "value": "Aer", "theme": ["Elven-inspired"], "tier": ["Apprentice", "Artisan", "Architect"] },

    { "type": "prefix", "value": "Kar", "theme": ["Dwarven-inspired"], "tier": ["Apprentice", "Artisan", "Architect"] },
    { "type": "prefix", "value": "Dur", "theme": ["Dwarven-inspired"], "tier": ["Apprentice", "Artisan", "Architect"] },
    { "type": "prefix", "value": "Balin", "theme": ["Dwarven-inspired"], "tier": ["Apprentice", "Artisan", "Architect"] },
    { "type": "prefix", "value": "Thra", "theme": ["Dwarven-inspired"], "tier": ["Apprentice", "Artisan", "Architect"] },
    { "type": "prefix", "value": "Ghim", "theme": ["Dwarven-inspired"], "tier": ["Apprentice", "Artisan", "Architect"] },
    { "type": "prefix", "value": "Khaz", "theme": ["Dwarven-inspired"], "tier": ["Apprentice", "Artisan", "Architect"] },
    { "type": "prefix", "value": "Tol", "theme": ["Dwarven-inspired"], "tier": ["Apprentice", "Artisan", "Architect"] },
    { "type": "prefix", "value": "Badur", "theme": ["Dwarven-inspired"], "tier": ["Apprentice", "Artisan", "Architect"] },
    { "type": "prefix", "value": "Kan", "theme": ["Dwarven-inspired"], "tier": ["Apprentice", "Artisan", "Architect"] },
    { "type": "prefix", "value": "Thrun", "theme": ["Dwarven-inspired"], "tier": ["Apprentice", "Artisan", "Architect"] },
    { "type": "prefix", "value": "Ton", "theme": ["Dwarven-inspired"], "tier": ["Apprentice", "Artisan", "Architect"] },
    { "type": "prefix", "value": "Tor", "theme": ["Dwarven-inspired"], "tier": ["Apprentice", "Artisan", "Architect"] },
    { "type": "prefix", "value": "Bord", "theme": ["Dwarven-inspired"], "tier": ["Apprentice", "Artisan", "Architect"] },
    { "type": "prefix", "value": "Gor", "theme": ["Dwarven-inspired"], "tier": ["Apprentice", "Artisan", "Architect"] },

    { "type": "prefix", "value": "Zar", "theme": ["Dark Elven-inspired"], "tier": ["Apprentice", "Artisan", "Architect"] },
    { "type": "prefix", "value": "Vel", "theme": ["Dark Elven-inspired"], "tier": ["Apprentice", "Artisan", "Architect"] },
    { "type": "prefix", "value": "Xil", "theme": ["Dark Elven-inspired"], "tier": ["Apprentice", "Artisan", "Architect"] },
    { "type": "prefix", "value": "Dru", "theme": ["Dark Elven-inspired"], "tier": ["Apprentice", "Artisan", "Architect"] },
    { "type": "prefix", "value": "Nal", "theme": ["Dark Elven-inspired"], "tier": ["Apprentice", "Artisan", "Architect"] },
    { "type": "prefix", "value": "Vhae", "theme": ["Dark Elven-inspired"], "tier": ["Apprentice", "Artisan", "Architect"] },
    { "type": "prefix", "value": "Lil", "theme": ["Dark Elven-inspired"], "tier": ["Apprentice", "Artisan", "Architect"] },

    { "type": "prefix", "value": "Skald", "theme": ["Nordic-inspired"], "tier": ["Artisan", "Architect"] },
    { "type": "prefix", "value": "Thor", "theme": ["Nordic-inspired"], "tags":["Fortress", "Capital"], "tier": ["Artisan", "Architect"] },
    { "type": "prefix", "value": "Bjorn", "theme": ["Nordic-inspired"], "tier": ["Artisan", "Architect"] },
    { "type": "prefix", "value": "Ulfr", "theme": ["Nordic-inspired"], "terrain":["Mountains", "Tundra", "Forest"],  "tags":["Remote", "Hidden", "Nomadic"], "tier": ["Artisan", "Architect"] },
    { "type": "prefix", "value": "Frost", "theme": ["Nordic-inspired"], "climate": ["Polar"], "terrain":["Mountains", "Tundra"], "tags":["Remote", "Border Post"], "tier": ["Artisan", "Architect"] },
    { "type": "prefix", "value": "Storm", "theme": ["Nordic-inspired"], "terrain":["Coast", "Hills", "Mountains"], "tags":["Port", "Trade Hub", "Military Outpost"], "tier": ["Artisan", "Architect"] },
    { "type": "prefix", "value": "Ravn", "theme": ["Nordic-inspired"], "tier": ["Artisan", "Architect"] },
    { "type": "prefix", "value": "Draug", "theme": ["Nordic-inspired"], "terrain":["Mountains", "Hills"], "tags":["Ancient Ruins", "Overgrown", "Infested"], "tier": ["Artisan", "Architect"] },
    { "type": "prefix", "value": "Vind", "theme": ["Nordic-inspired"], "tier": ["Artisan", "Architect"] },
    { "type": "prefix", "value": "Hrafn", "theme": ["Nordic-inspired"], "tier": ["Artisan", "Architect"] }
]